zfnet/__init__.py
zfnet/conn.py
zfnet/decomp.py
zfnet/io.py
zfnet/isomorphic_matching.py
zfnet/utils.py
zfnet/visualize.py
zfnet-0.0.6.dist-info/licenses/LICENSE
zfnet-0.0.6.dist-info/METADATA
zfnet-0.0.6.dist-info/WHEEL
zfnet-0.0.6.dist-info/top_level.txt
zfnet-0.0.6.dist-info/RECORD
